seye/__init__.py
seye/_torch_impl.py
seye/spherical_projection.py
seye/version.py
seye-0.0.0.dist-info/METADATA
seye-0.0.0.dist-info/WHEEL
seye-0.0.0.dist-info/top_level.txt
seye-0.0.0.dist-info/RECORD
